MUX/MUX2to1.v
module MUX2to1(c, a, b, sel);
output c;
input a, b, sel;

//dataflow level
assign c = (a&sel) | (b&(!sel));

endmodule

MUX/MUX2to1_tb.v
`timescale 1ns/1ps
module MUX2to1_tb;

    // 信號宣告
    wire c;
    reg a;
    reg b;
    reg sel;

    // 模塊實例化
    MUX2to1 uut (
        .c(c),
        .a(a),
        .b(b),
        .sel(sel)
    );

    // 測試激勵邏輯
    initial begin
        // 初始化輸入信號
        a = 1'b0;
        b = 1'b1;
        sel = 1'b0;
        #20;

        // 隨機變化輸入信號
        // 第 1 次變化
        a = 1'b0;
        b = 1'b0;
        sel = 1'b1;
        #20;
        // 第 2 次變化
        a = 1'b1;
        b = 1'b1;
        sel = 1'b1;
        #20;
        // 第 3 次變化
        a = 1'b1;
        b = 1'b0;
        sel = 1'b0;
        #20;
        // 第 4 次變化
        a = 1'b1;
        b = 1'b1;
        sel = 1'b1;
        #20;
        // 第 5 次變化
        a = 1'b0;
        b = 1'b0;
        sel = 1'b1;
        #20;
        // 第 6 次變化
        a = 1'b0;
        b = 1'b1;
        sel = 1'b0;
        #20;
        // 第 7 次變化
        a = 1'b0;
        b = 1'b1;
        sel = 1'b0;
        #20;
        // 第 8 次變化
        a = 1'b1;
        b = 1'b0;
        sel = 1'b1;
        #20;
        // 第 9 次變化
        a = 1'b1;
        b = 1'b1;
        sel = 1'b0;
        #20;
        // 第 10 次變化
        a = 1'b0;
        b = 1'b1;
        sel = 1'b1;
        #20;

        // 結束模擬
        #100;
        $finish;
    end

    // 輸出監控
    initial begin
        $monitor("Time=%0d, c=%b, a=%b, b=%b, sel=%b", $time, c, a, b, sel);
    end

    initial begin
        $dumpfile("MUX2to1_tb.vcd");
        $dumpvars;
    end

endmodule

MUX/MUX2to1_tb.vcd
$date
	Sun Nov 10 01:13:19 2024
$end
$version
	Icarus Verilog
$end
$timescale
	1ps
$end
$scope module MUX2to1_tb $end
$var wire 1 ! c $end
$var reg 1 " a $end
$var reg 1 # b $end
$var reg 1 $ sel $end
$scope module uut $end
$var wire 1 " a $end
$var wire 1 # b $end
$var wire 1 ! c $end
$var wire 1 $ sel $end
$upscope $end
$upscope $end
$enddefinitions $end
$comment Show the parameter values. $end
$dumpall
$end
#0
$dumpvars
0$
1#
0"
1!
$end
#20000
0!
1$
0#
#40000
1!
1#
1"
#60000
0!
0$
0#
#80000
1!
1$
1#
#100000
0!
0#
0"
#120000
1!
0$
1#
#160000
1$
0#
1"
#180000
0$
1#
#200000
0!
1$
0"
